mmodes/Experiment.py
mmodes/__init__.py
mmodes/_fsolvers.py
mmodes/core.py
mmodes/mmodes.py
mmodes/io/__init__.py
mmodes/io/io.py
mmodes/io/models_in.py
mmodes/vis/__init__.py
mmodes/vis/vis.py
mmodes-0.2.6.dist-info/LICENSE.txt
mmodes-0.2.6.dist-info/METADATA
mmodes-0.2.6.dist-info/WHEEL
mmodes-0.2.6.dist-info/top_level.txt
mmodes-0.2.6.dist-info/RECORD
